hydutils/__init__.py
hydutils/df_helper.py
hydutils/hydrology_constants.py
hydutils/statistical_metrics.py
hydutils-2.0.0.dist-info/LICENSE
hydutils-2.0.0.dist-info/METADATA
hydutils-2.0.0.dist-info/WHEEL
hydutils-2.0.0.dist-info/RECORD
